subsetzer_gui/__init__.py
subsetzer_gui/app.py
subsetzer_gui/py.typed
subsetzer_gui-0.1.4.dist-info/METADATA
subsetzer_gui-0.1.4.dist-info/WHEEL
subsetzer_gui-0.1.4.dist-info/entry_points.txt
subsetzer_gui-0.1.4.dist-info/licenses/LICENSE
subsetzer_gui-0.1.4.dist-info/RECORD
