Metadata-Version: 2.4
Name: subsetzer-gui
Version: 0.1.4
Summary: Tk-based GUI for Subsetzer.
Project-URL: Homepage, https://github.com/githabideri/subsetzer
Project-URL: Issues, https://github.com/githabideri/subsetzer/issues
Author-email: Martin Fellner <martin@martinfellner.at>
License-Expression: GPL-3.0-or-later
License-File: LICENSE
Requires-Python: >=3.9
Requires-Dist: subsetzer>=0.1.4
